Metadata-Version: 2.1
Name: VerifyKit
Version: 0.4
Summary: VerifyKit is the next gen phone number validation system. Users can easily verify their phone numbers without the need of entering phone number or a pin code.
Home-page: https://github.com/verifykit/verifykit-sdk-python
Author: VerifyKit
Author-email: sdk@verifykit.com
License: UNKNOWN
Download-URL: https://github.com/verifykit/verifykit-sdk-python/archive/master.zip
Keywords: verifykit,
Platform: UNKNOWN
